{
  "project_info": {
    "project_number": "973470529047",
    "project_id": "titik-kumpul-6b913",
    "storage_bucket": "titik-kumpul-6b913.firebasestorage.app"
  },
  "client": [
    {
      "client_info": {
        "mobilesdk_app_id": "1:973470529047:android:6fe02f7436ba81cecbce52",
        "android_client_info": {
          "package_name": "com.example.campus_food_recommender"
        }
      },
      "oauth_client": [],
      "api_key": [
        {
          "current_key": "AIzaSyCy7O8XD0whXO0pTcS4aZy9BhkgfLwiaDw"
        }
      ],
      "services": {
        "appinvite_service": {
          "other_platform_oauth_client": []
        }
      }
    }
  ],
  "configuration_version": "1"
}